{
  "Iphone": {
    "Iphone 4": {
      "d5c7004fc69c8fc058a2c5f9e650cf10": {
        "product_name": "Inkax USB Data Cable iPhone 4/4S",
        "price": "$3.63",
        "price_value": "3.63",
        "public_price": "$6.60",
        "product_url": "http://jstech.com.au/for-iphone/i-phone-4/inkax-usb-data-cable-iphone-4-4s.html",
        "old_price": "$3.63",
        "old_price_value": "3.63",
        "is_changed": false,
        "diff": 0
      },
      "c1f7b6d82c7e846eb2a224b22255cfe1": {
        "product_name": "iPhone 4 4s Battery Adhesive Sticke",
        "price": "$0.88",
        "price_value": "0.88",
        "public_price": "$1.65",
        "product_url": "http://jstech.com.au/for-iphone/i-phone-4/iphone-4-battery-adhesive-sticker.html",
        "old_price": "$0.88",
        "old_price_value": "0.88",
        "is_changed": false,
        "diff": 0
      },
      "20d4c162065b0df602031edb31ca89de": {
        "product_name": "iPhone 4 4s Dummy Phone",
        "price": "$5.50",
        "price_value": "5.50",
        "public_price": "$8.80",
        "product_url": "http://jstech.com.au/for-iphone/i-phone-4/iphone-4-4s-black-dummy-phone.html",
        "old_price": "$5.50",
        "old_price_value": "5.50",
        "is_changed": false,
        "diff": 0
      },
      "f8ad047a3939819420756da98d8866a9": {
        "product_name": "iPhone 4 4s Ear and Loud Speaker Me",
        "price": "$0.88",
        "price_value": "0.88",
        "public_price": "$2.20",
        "product_url": "http://jstech.com.au/for-iphone/i-phone-4/iphone-4-ear-and-loud-speaker-mesh.html",
        "old_price": "$0.88",
        "old_price_value": "0.88",
        "is_changed": false,
        "diff": 0
      },
      "d9c51eff437df0085077e614fb328aa5": {
        "product_name": "iPhone 4 4s LCD Testing Cable",
        "price": "$3.85",
        "price_value": "3.85",
        "public_price": "$7.70",
        "product_url": "http://jstech.com.au/for-iphone/i-phone-4/iphone-4-4s-lcd-testing-cable.html",
        "old_price": "$3.85",
        "old_price_value": "3.85",
        "is_changed": false,
        "diff": 0
      },
      "3f887e0494f4b14cbd8c05b5bbf6e48a": {
        "product_name": "iPhone 4 4s Nillkin Glistening Seri",
        "price": "$5.50",
        "price_value": "5.50",
        "public_price": "$11.00",
        "product_url": "http://jstech.com.au/for-iphone/i-phone-4/iphone-4-4s-nillkin-glistening-series-case-black.html",
        "old_price": "$5.50",
        "old_price_value": "5.50",
        "is_changed": false,
        "diff": 0
      },
      "dcfdd072692f017c0ece6efb0af6ba47": {
        "product_name": "iPhone 4 4s Nillkin Q Series Case B",
        "price": "$5.50",
        "price_value": "5.50",
        "public_price": "$11.00",
        "product_url": "http://jstech.com.au/for-iphone/i-phone-4/iphone-4-4s-nillkin-q-series-case-blue.html",
        "old_price": "$5.50",
        "old_price_value": "5.50",
        "is_changed": false,
        "diff": 0
      },
      "2b0ad7ffc8819444b23b433c3405f350": {
        "product_name": "iPhone 4 4s Nillkin Q Series Case P",
        "price": "$6.05",
        "price_value": "6.05",
        "public_price": "$9.90",
        "product_url": "http://jstech.com.au/for-iphone/i-phone-4/iphone-4-4s-nillkin-q-series-case-pink.html",
        "old_price": "$6.05",
        "old_price_value": "6.05",
        "is_changed": false,
        "diff": 0
      },
      "59a2fadfbfb60ba11186117e976e5128": {
        "product_name": "iPhone 4 4s Nillkin Q Series Case Y",
        "price": "$5.50",
        "price_value": "5.50",
        "public_price": "$11.00",
        "product_url": "http://jstech.com.au/for-iphone/i-phone-4/iphone-4-4s-nillkin-q-series-case-yellow.html",
        "old_price": "$5.50",
        "old_price_value": "5.50",
        "is_changed": false,
        "diff": 0
      },
      "4ccd097717de619b431685ea215f5ed4": {
        "product_name": "iPhone 4 4s Power Volume Button Kit",
        "price": "$1.65",
        "price_value": "1.65",
        "public_price": "$3.30",
        "product_url": "http://jstech.com.au/for-iphone/i-phone-4/iphone-4-power-volume-button-kit.html",
        "old_price": "$1.65",
        "old_price_value": "1.65",
        "is_changed": false,
        "diff": 0
      },
      "3dd7931f5b787023598445f2a1fe592a": {
        "product_name": "iPhone 4 4s Sim Tray Replacement",
        "price": "$3.30",
        "price_value": "3.30",
        "public_price": "$6.60",
        "product_url": "http://jstech.com.au/for-iphone/i-phone-4/iphone-4s-sim-tray-replacement.html",
        "old_price": "$3.30",
        "old_price_value": "3.30",
        "is_changed": false,
        "diff": 0
      },
      "fa9a76124d9368f965f91b6873e56b41": {
        "product_name": "iPhone 4 4s Star Screw set - Bottom",
        "price": "$0.55",
        "price_value": "0.55",
        "public_price": "$2.20",
        "product_url": "http://jstech.com.au/for-iphone/i-phone-4/iphone-4-5-star-screw-set-bottom.html",
        "old_price": "$0.55",
        "old_price_value": "0.55",
        "is_changed": false,
        "diff": 0
      },
      "0c21c08c169f93afaea3bd13aaf51916": {
        "product_name": "iPhone 4 4s Tempered Glass Screen",
        "price": "$2.53",
        "price_value": "2.53",
        "public_price": "$5.50",
        "product_url": "http://jstech.com.au/for-iphone/i-phone-4/iphone-4-4s-tempered-glass-screen.html",
        "old_price": "$2.53",
        "old_price_value": "2.53",
        "is_changed": false,
        "diff": 0
      },
      "b72f7d03875f8bca56338e594f636eb6": {
        "product_name": "iPhone 4 Audio Jack Flex Replacemen",
        "price": "$3.85",
        "price_value": "3.85",
        "public_price": "$7.70",
        "product_url": "http://jstech.com.au/for-iphone/i-phone-4/iphone-4-audio-jack-flex-replacement.html",
        "old_price": "$3.85",
        "old_price_value": "3.85",
        "is_changed": false,
        "diff": 0
      },
      "b38330ea48f7d6bf26a08337828a62d0": {
        "product_name": "iPhone 4 Back Camera Replacement",
        "price": "$7.70",
        "price_value": "7.70",
        "public_price": "$13.20",
        "product_url": "http://jstech.com.au/for-iphone/i-phone-4/iphone-4-back-camera-replacement.html",
        "old_price": "$7.70",
        "old_price_value": "7.70",
        "is_changed": false,
        "diff": 0
      },
      "a95418a0069edb3cc0b22241ba11ffc2": {
        "product_name": "iPhone 4 Back Glass Replacement Bla",
        "price": "$3.85",
        "price_value": "3.85",
        "public_price": "$7.70",
        "product_url": "http://jstech.com.au/for-iphone/i-phone-4/iphone-4-back-glass-replacement-black.html",
        "old_price": "$3.85",
        "old_price_value": "3.85",
        "is_changed": false,
        "diff": 0
      },
      "bec8eb265f9ce33fd73b4719fb2228a2": {
        "product_name": "iPhone 4 Back Glass Replacement Whi",
        "price": "$3.85",
        "price_value": "3.85",
        "public_price": "$7.70",
        "product_url": "http://jstech.com.au/for-iphone/i-phone-4/iphone-4-back-glass-replacement-white.html",
        "old_price": "$3.85",
        "old_price_value": "3.85",
        "is_changed": false,
        "diff": 0
      },
      "cc1e28e8dae21629e59c305c8678edf1": {
        "product_name": "iPhone 4 Battery Connector FPC Plug",
        "price": "$3.85",
        "price_value": "3.85",
        "public_price": "$7.70",
        "product_url": "http://jstech.com.au/for-iphone/i-phone-4/iphone-4-battery-connector-fpc-plug.html",
        "old_price": "$3.85",
        "old_price_value": "3.85",
        "is_changed": false,
        "diff": 0
      },
      "86f192f05a4fb4b64689edc44080f508": {
        "product_name": "iPhone 4 Battery Replacement",
        "price": "$9.35",
        "price_value": "9.35",
        "public_price": "$11.00",
        "product_url": "http://jstech.com.au/for-iphone/i-phone-4/iphone-4-battery-replacement.html",
        "old_price": "$9.35",
        "old_price_value": "9.35",
        "is_changed": false,
        "diff": 0
      },
      "b886b013a7027812970363347c7f621f": {
        "product_name": "iPhone 4 Charge Flex Black",
        "price": "$4.40",
        "price_value": "4.40",
        "public_price": "$7.70",
        "product_url": "http://jstech.com.au/for-iphone/i-phone-4/iphone-4-charge-port-flex-replacement.html",
        "old_price": "$4.40",
        "old_price_value": "4.40",
        "is_changed": false,
        "diff": 0
      },
      "e7db5ad3346cc57352fa061db5130261": {
        "product_name": "iPhone 4 Charge Flex White",
        "price": "$3.85",
        "price_value": "3.85",
        "public_price": "$7.70",
        "product_url": "http://jstech.com.au/for-iphone/i-phone-4/iphone-4-charge-port-replacement-flex-white.html",
        "old_price": "$3.85",
        "old_price_value": "3.85",
        "is_changed": false,
        "diff": 0
      },
      "29fc42114d1a1bb44293d4a569f73e8a": {
        "product_name": "iPhone 4 Complete Screw set",
        "price": "$2.75",
        "price_value": "2.75",
        "public_price": "$5.50",
        "product_url": "http://jstech.com.au/for-iphone/i-phone-4/iphone-4-complete-screw-set.html",
        "old_price": "$2.75",
        "old_price_value": "2.75",
        "is_changed": false,
        "diff": 0
      },
      "a093870b4ea55f11cd28141b981f223c": {
        "product_name": "iPhone 4 Digitizer FPC Plug",
        "price": "$3.85",
        "price_value": "3.85",
        "public_price": "$5.50",
        "product_url": "http://jstech.com.au/for-iphone/i-phone-4/iphone-4-digitizer-fpc-plug.html",
        "old_price": "$3.85",
        "old_price_value": "3.85",
        "is_changed": false,
        "diff": 0
      },
      "4d6a285609002cd5671e924f4989b106": {
        "product_name": "iPhone 4 Ear Piece Speaker Replacem",
        "price": "$1.65",
        "price_value": "1.65",
        "public_price": "$3.30",
        "product_url": "http://jstech.com.au/for-iphone/i-phone-4/iphone-4-ear-piece-speaker-replacement.html",
        "old_price": "$1.65",
        "old_price_value": "1.65",
        "is_changed": false,
        "diff": 0
      },
      "54dcdd780f6e457b9d6f40323bd1d0b5": {
        "product_name": "iPhone 4 Front Camera Replacement",
        "price": "$3.30",
        "price_value": "$3.30undefined",
        "public_price": "$5.50",
        "product_url": "http://jstech.com.au/for-iphone/i-phone-4/iphone-4-front-camera-replacement.html",
        "old_price": "$3.30",
        "old_price_value": "$3.30undefined",
        "is_changed": true,
        "diff": null
      },
      "f8a8009a7ad60fed32eb362e64312d8d": {
        "product_name": "iPhone 4 Home Button + Flex Black",
        "price": "$1.32",
        "price_value": "$1.32undefined",
        "public_price": "$2.75",
        "product_url": "http://jstech.com.au/for-iphone/i-phone-4/iphone-4-home-button-flex-black.html",
        "old_price": "$1.32",
        "old_price_value": "$1.32undefined",
        "is_changed": true,
        "diff": null
      },
      "50ac1f1c159ece8e2ecb94fd392ebe08": {
        "product_name": "iPhone 4 Home Button + Flex White",
        "price": "$1.32",
        "price_value": "$1.32undefined",
        "public_price": "$2.75",
        "product_url": "http://jstech.com.au/for-iphone/i-phone-4/iphone-4-home-button-flex-white.html",
        "old_price": "$1.32",
        "old_price_value": "$1.32undefined",
        "is_changed": true,
        "diff": null
      },
      "614b8473188902ce63a38c06fc5c617e": {
        "product_name": "iPhone 4 Home Button Flex",
        "price": "$0.88",
        "price_value": "$0.88undefined",
        "public_price": "$1.65",
        "product_url": "http://jstech.com.au/for-iphone/i-phone-4/iphone-4-home-button-flex-cable.html",
        "old_price": "$0.88",
        "old_price_value": "$0.88undefined",
        "is_changed": true,
        "diff": null
      },
      "1dd02f53e0b87c26f8ca9797255e6604": {
        "product_name": "iPhone 4 Home Button Replacement",
        "price": "$0.55",
        "price_value": "$0.55undefined",
        "public_price": "$0.99",
        "product_url": "http://jstech.com.au/for-iphone/i-phone-4/iphone-4-home-button-replacement.html",
        "old_price": "$0.55",
        "old_price_value": "$0.55undefined",
        "is_changed": true,
        "diff": null
      },
      "e63cd808333b9dc5ed9b209be016c264": {
        "product_name": "iPhone 4 Home Button Replacement Red",
        "price": "$0.55",
        "price_value": "$0.55undefined",
        "public_price": "$0.99",
        "product_url": "http://jstech.com.au/for-iphone/i-phone-4/iphone-4-home-button-replacement-red.html",
        "old_price": "$0.55",
        "old_price_value": "$0.55undefined",
        "is_changed": true,
        "diff": null
      },
      "ee4d6db0b2289c2060077f0bfa0c8f8f": {
        "product_name": "iPhone 4 LCD Digitizer Black Grade A",
        "price": "$20.90",
        "price_value": "$20.90undefined",
        "public_price": "$27.50",
        "product_url": "http://jstech.com.au/for-iphone/i-phone-4/iphone-4-lcd-digitizer-black.html",
        "old_price": "$20.90",
        "old_price_value": "$20.90undefined",
        "is_changed": true,
        "diff": null
      },
      "70438aae4fe73711f27fecbbf6cd90a7": {
        "product_name": "iPhone 4 LCD Digitizer Grade A White",
        "price": "$20.90",
        "price_value": "$20.90undefined",
        "public_price": "$27.50",
        "product_url": "http://jstech.com.au/for-iphone/i-phone-4/iphone-4-lcd-digitizer-grade-a-white.html",
        "old_price": "$20.90",
        "old_price_value": "$20.90undefined",
        "is_changed": true,
        "diff": null
      },
      "e52d8ad54dbf2ddeda05a624a6fb8ec0": {
        "product_name": "iPhone 4 LCD Digitizer Grade AAA Black",
        "price": "$27.50",
        "price_value": "$27.50undefined",
        "public_price": "$34.10",
        "product_url": "http://jstech.com.au/for-iphone/i-phone-4/iphone-4-lcd-digitizer-grade-aaa-black.html",
        "old_price": "$27.50",
        "old_price_value": "$27.50undefined",
        "is_changed": true,
        "diff": null
      },
      "df2632af8afc99bdefefb655e62f9a85": {
        "product_name": "iPhone 4 LCD Digitizer Grade AAA White",
        "price": "$27.50",
        "price_value": "$27.50undefined",
        "public_price": "$35.20",
        "product_url": "http://jstech.com.au/for-iphone/i-phone-4/iphone-4-lcd-digitizer-grade-aaa-white.html",
        "old_price": "$27.50",
        "old_price_value": "$27.50undefined",
        "is_changed": true,
        "diff": null
      },
      "4474b0949e8e32ce1c1e0b51c000f1ba": {
        "product_name": "iPhone 4 LCD FPC Plug",
        "price": "$3.30",
        "price_value": "$3.30undefined",
        "public_price": "$5.50",
        "product_url": "http://jstech.com.au/for-iphone/i-phone-4/iphone-4-lcd-fpc-plug.html",
        "old_price": "$3.30",
        "old_price_value": "$3.30undefined",
        "is_changed": true,
        "diff": null
      },
      "10939bbf8b0ee97fe5cad3bd5c77573d": {
        "product_name": "iPhone 4 LoudSpeaker Replacement",
        "price": "$2.75",
        "price_value": "$2.75undefined",
        "public_price": "$4.40",
        "product_url": "http://jstech.com.au/for-iphone/i-phone-4/iphone-4-loudspeaker-replacement.html",
        "old_price": "$2.75",
        "old_price_value": "$2.75undefined",
        "is_changed": true,
        "diff": null
      },
      "f7ffd09b1d324c6eac73f5e9018332ff": {
        "product_name": "iPhone 4 Mid Frame Full Assembly Replacement",
        "price": "$37.40",
        "price_value": "$37.40undefined",
        "public_price": "$44.00",
        "product_url": "http://jstech.com.au/for-iphone/i-phone-4/iphone-4-mid-frame-full-assembly-replacement.html",
        "old_price": "$37.40",
        "old_price_value": "$37.40undefined",
        "is_changed": true,
        "diff": null
      },
      "ec2ff872345f20e59b458a5c75dee8f2": {
        "product_name": "iPhone 4 Mid Frame Replacement",
        "price": "$24.20",
        "price_value": "$24.20undefined",
        "public_price": "$28.60",
        "product_url": "http://jstech.com.au/for-iphone/i-phone-4/iphone-4-mid-frame-replacement.html",
        "old_price": "$24.20",
        "old_price_value": "$24.20undefined",
        "is_changed": true,
        "diff": null
      },
      "a09fa410e5740c638545d00d021ccee1": {
        "product_name": "iPhone 4 Proximity Sensor Replacement",
        "price": "$3.30",
        "price_value": "$3.30undefined",
        "public_price": "$5.50",
        "product_url": "http://jstech.com.au/for-iphone/i-phone-4/iphone-4-proximity-sensor-replacement.html",
        "old_price": "$3.30",
        "old_price_value": "$3.30undefined",
        "is_changed": true,
        "diff": null
      },
      "4837e55090cda364197435d1c3d747ab": {
        "product_name": "iPhone 4 Screen Protector Transparent",
        "price": "$0.55",
        "price_value": "$0.55undefined",
        "public_price": "$0.99",
        "product_url": "http://jstech.com.au/for-iphone/i-phone-4/iphone-4-screen-protector-transparent.html",
        "old_price": "$0.55",
        "old_price_value": "$0.55undefined",
        "is_changed": true,
        "diff": null
      },
      "e9628e3be47b0932f2a6fb6311d549cb": {
        "product_name": "iPhone 4 Screw Mat Holder Distribution",
        "price": "$1.65",
        "price_value": "$1.65undefined",
        "public_price": "$3.30",
        "product_url": "http://jstech.com.au/for-iphone/i-phone-4/iphone-4-screw-mat-holder-distribution.html",
        "old_price": "$1.65",
        "old_price_value": "$1.65undefined",
        "is_changed": true,
        "diff": null
      },
      "d1f23fe2949be128d5dec0955faa6f7a": {
        "product_name": "iPhone 4 Speaker Antenna Assembly",
        "price": "$3.85",
        "price_value": "$3.85undefined",
        "public_price": "$7.70",
        "product_url": "http://jstech.com.au/for-iphone/i-phone-4/iphone-4-speaker-antenna-assembly.html",
        "old_price": "$3.85",
        "old_price_value": "$3.85undefined",
        "is_changed": true,
        "diff": null
      },
      "b82c24df0af04efc914e67bde0bda0de": {
        "product_name": "iPhone 4 Vibration Motor",
        "price": "$3.85",
        "price_value": "$3.85undefined",
        "public_price": "$7.70",
        "product_url": "http://jstech.com.au/for-iphone/i-phone-4/iphone-4-vibration-motor.html",
        "old_price": "$3.85",
        "old_price_value": "$3.85undefined",
        "is_changed": true,
        "diff": null
      },
      "52a6c9632ce774c2ab1b69b54ec5617f": {
        "product_name": "iPhone 4 WiFi Flex Cable",
        "price": "$3.30",
        "price_value": "$3.30undefined",
        "public_price": "$5.50",
        "product_url": "http://jstech.com.au/for-iphone/i-phone-4/iphone-4-wifi-flex-cable.html",
        "old_price": "$3.30",
        "old_price_value": "$3.30undefined",
        "is_changed": true,
        "diff": null
      },
      "deacdc146555a4a124acd0311dfbaad8": {
        "product_name": "iPhone 4/4s iPad Lightning Charging Cable ",
        "price": "$5.50",
        "price_value": "$5.50undefined",
        "public_price": "$8.80",
        "product_url": "http://jstech.com.au/for-iphone/i-phone-4/iphone-4-4s-lightning-chargeing-cable.html",
        "old_price": "$5.50",
        "old_price_value": "$5.50undefined",
        "is_changed": true,
        "diff": null
      },
      "84e535e0d05c1f436e70315606cf7bfa": {
        "product_name": "Kid's Case Minions for Iphone 4G",
        "price": "$4.90",
        "price_value": "$4.90undefined",
        "public_price": "$8.75",
        "product_url": "http://jstech.com.au/for-iphone/i-phone-4/kids-case-minions-for-iphone-4g.html",
        "old_price": "$4.90",
        "old_price_value": "$4.90undefined",
        "is_changed": true,
        "diff": null
      },
      "fd55c89c75e88ec38e7e9894619746e0": {
        "product_name": "Kingleen USB Data Cable iPhone 4/4S K-04",
        "price": "$3.85",
        "price_value": "$3.85undefined",
        "public_price": "$7.70",
        "product_url": "http://jstech.com.au/for-iphone/i-phone-4/kingleen-usb-data-cable-iphone-4-4s-k-04.html",
        "old_price": "$3.85",
        "old_price_value": "$3.85undefined",
        "is_changed": true,
        "diff": null
      },
      "41ddfcd703e16af91a78397af4101ee3": {
        "product_name": "Noosey Nano Micro Sim Adapter",
        "price": "$3.30",
        "price_value": "$3.30undefined",
        "public_price": "$6.60",
        "product_url": "http://jstech.com.au/for-iphone/i-phone-4/nano-micro-sim-adapter.html",
        "old_price": "$3.30",
        "old_price_value": "$3.30undefined",
        "is_changed": true,
        "diff": null
      },
      "7c06cf73713d4cf5c7af2e5a5f9b668e": {
        "product_name": "Pielcedan Leather Case for iPhone 4",
        "price": "$3.85",
        "price_value": "$3.85undefined",
        "public_price": "$10.78",
        "product_url": "http://jstech.com.au/for-iphone/i-phone-4/pielcedan-leather-case-for-iphone-4.html",
        "old_price": "$3.85",
        "old_price_value": "$3.85undefined",
        "is_changed": true,
        "diff": null
      },
      "8158ed89b2f2d88eec4fb615a77c285c": {
        "product_name": "Power Bank Case For iPhone 4/4s 3000mah",
        "price": "$28.59",
        "price_value": "$28.59undefined",
        "public_price": "$28.59",
        "product_url": "http://jstech.com.au/for-iphone/i-phone-4/power-bank-case-for-iphone-4-4s.html",
        "old_price": "$28.59",
        "old_price_value": "$28.59undefined",
        "is_changed": true,
        "diff": null
      },
      "9475ee575485e9beefc48d2504a82bbd": {
        "product_name": "iPhone 4 4s Nillkin Glistening Series Case Red",
        "price": "$5.50",
        "price_value": "$5.50undefined",
        "public_price": "$11.00",
        "product_url": "http://jstech.com.au/for-iphone/i-phone-4/iphone-4-4s-nillkin-glistening-series-case-red.html",
        "old_price": "$5.50",
        "old_price_value": "$5.50undefined",
        "is_changed": true,
        "diff": null
      }
    }
  }
}